[{"buildOrder":717,"reportUrl":"https://NPGW.github.io/npgw-ui-test/717/","reportName":"Allure Report with history","data":{"run":104,"retry":3}},{"buildOrder":717,"reportUrl":"https://NPGW.github.io/npgw-ui-test/717/","reportName":"Allure Report with history","data":{"run":104,"retry":1}},{"buildOrder":716,"reportUrl":"https://NPGW.github.io/npgw-ui-test/716/","reportName":"Allure Report with history","data":{"run":104,"retry":1}},{"buildOrder":715,"reportUrl":"https://NPGW.github.io/npgw-ui-test/715/","reportName":"Allure Report with history","data":{"run":104,"retry":1}},{"buildOrder":714,"reportUrl":"https://NPGW.github.io/npgw-ui-test/714/","reportName":"Allure Report with history","data":{"run":106,"retry":0}},{"buildOrder":713,"reportUrl":"https://NPGW.github.io/npgw-ui-test/713/","reportName":"Allure Report with history","data":{"run":106,"retry":0}},{"buildOrder":712,"reportUrl":"https://NPGW.github.io/npgw-ui-test/712/","reportName":"Allure Report with history","data":{"run":104,"retry":1}},{"data":{"run":0,"retry":0}}]